pypore3d/p3dBlob.py
pypore3d/_p3dBlob.cpython-311-x86_64-linux-gnu.so
pypore3d/_p3dFilt.cpython-311-x86_64-linux-gnu.so
pypore3d/p3dFiltPy_16.py
pypore3d/p3dSkelPy.py
pypore3d/p3dSkel.py
pypore3d/p3d_common_lib.py
pypore3d/p3dSITKPy.py
pypore3d/_p3dSkel.cpython-311-x86_64-linux-gnu.so
pypore3d/p3dSITKPy_16.py
pypore3d/p3d_SITK_common_lib_16.py
pypore3d/p3dBlobPy.py
pypore3d/setup.py
pypore3d/p3dFiltPy.py
pypore3d/__init__.py
pypore3d/p3d_SITK_common_lib.py
pypore3d/p3dFilt.py
pypore3d/p3d_SITK_read_raw.py
pypore3d/pypore3d/p3dBlob.py
pypore3d/pypore3d/p3dFiltPy_16.py
pypore3d/pypore3d/p3dSkelPy.py
pypore3d/pypore3d/p3dSkel.py
pypore3d/pypore3d/p3d_common_lib.py
pypore3d/pypore3d/p3dSITKPy.py
pypore3d/pypore3d/p3dSITKPy_16.py
pypore3d/pypore3d/p3d_SITK_common_lib_16.py
pypore3d/pypore3d/p3dBlobPy.py
pypore3d/pypore3d/p3dFiltPy.py
pypore3d/pypore3d/__init__.py
pypore3d/pypore3d/p3d_SITK_common_lib.py
pypore3d/pypore3d/p3dFilt.py
pypore3d/pypore3d/p3d_SITK_read_raw.py
multi_version_pypore3d_test-0.0.4.dist-info/WHEEL
multi_version_pypore3d_test-0.0.4.dist-info/LICENSE
multi_version_pypore3d_test-0.0.4.dist-info/RECORD
multi_version_pypore3d_test-0.0.4.dist-info/METADATA
multi_version_pypore3d_test-0.0.4.dist-info/top_level.txt
